autoafids/__init__.py
autoafids/config/snakebids.yml
autoafids/pipeline_description.json
autoafids/resources/dummy.fcsv
autoafids/resources/tpl-MNI152NLin2009cAsym_res-01_T1w.fcsv
autoafids/resources/tpl-MNI152NLin2009cAsym_res-01_T1w.nii.gz
autoafids/resources/tpl-MNI152NLin2009cAsym_res-01_T2w.nii.gz
autoafids/resources/tpl-MNI152NLin2009cAsym_res-01_desc-groundtruth_afids.fcsv
autoafids/run.py
autoafids/workflow/Snakefile
autoafids/workflow/rules/cnn.smk
autoafids/workflow/scripts/apply.py
autoafids/workflow/scripts/n4_bias_corr.py
autoafids/workflow/scripts/norm_schemes.py
autoafids/workflow/scripts/regis_script.py
autoafids/workflow/scripts/resample_img.py
autoafids/workflow/scripts/tform_script.py
autoafids/workflow/scripts/utils.py
autoafids-0.1.4.dist-info/LICENSE
autoafids-0.1.4.dist-info/METADATA
autoafids-0.1.4.dist-info/WHEEL
autoafids-0.1.4.dist-info/entry_points.txt
autoafids-0.1.4.dist-info/RECORD
