Metadata-Version: 2.1
Name: autoafids
Version: 0.1.4
Summary: End-to-end SnakeBIDS workflow for landmark regression and derivative apps 
Author: Alaa Taha
Author-email: ataha24@uwo.ca
Requires-Python: >=3.8,<3.12
Classifier: Programming Language :: Python :: 3
Classifier: Programming Language :: Python :: 3.8
Classifier: Programming Language :: Python :: 3.9
Classifier: Programming Language :: Python :: 3.10
Classifier: Programming Language :: Python :: 3.11
Requires-Dist: antspyx (>=0.5.3,<0.6.0)
Requires-Dist: appdirs (>=1.4.4,<2.0.0)
Requires-Dist: nilearn (>=0.10.3,<0.11.0)
Requires-Dist: pandas (>=2.0.3,<3.0.0)
Requires-Dist: pulp (<2.6.0)
Requires-Dist: scikit-image (>=0.19.3,<0.20.0)
Requires-Dist: snakebids (>=0.13.1)
Requires-Dist: tensorflow (>=2.12.0,<2.16.0)
